{
  "gitSyncId": "66cfa4c28eb6fc0fd11d8a6b_7da5e0a5-3229-4f4f-b7b0-da04b68997d1",
  "id": "Table from DB_Here",
  "pluginId": "restapi-plugin",
  "pluginType": "API",
  "unpublishedAction": {
    "actionConfiguration": {
      "autoGeneratedHeaders": [],
      "body": "",
      "bodyFormData": [],
      "encodeParamsToggle": true,
      "formData": {
        "apiContentType": "none"
      },
      "headers": [
        {
          "key": "apikey",
          "value": "8BEB3_3nVcZElU8m5xdhEJvQ482CNVSBNUV5MN6KprY"
        }
      ],
      "httpMethod": "GET",
      "httpVersion": "HTTP11",
      "paginationType": "NONE",
      "pluginSpecifiedTemplates": [
        {
          "value": true
        }
      ],
      "queryParameters": [],
      "timeoutInMillisecond": 10000
    },
    "confirmBeforeExecute": false,
    "datasource": {
      "isAutoGenerated": false,
      "name": "DEFAULT_REST_DATASOURCE",
      "pluginId": "restapi-plugin"
    },
    "dynamicBindingPathList": [],
    "executeOnLoad": false,
    "name": "Here",
    "pageId": "Table from DB",
    "userSetOnLoad": false
  }
}