{
  "accentColor": "{{appsmith.theme.colors.primaryColor}}",
  "animateLoading": true,
  "backgroundColor": "#FFFFFF",
  "borderColor": "#E0DEDE",
  "borderRadius": "0.375rem",
  "borderWidth": 1,
  "bottomRow": 72,
  "boxShadow": "none",
  "children": [
    {
      "borderRadius": "{{appsmith.theme.borderRadius.appBorderRadius}}",
      "bottomRow": 680,
      "boxShadow": "{{appsmith.theme.boxShadow.appBoxShadow}}",
      "canExtend": true,
      "detachFromLayout": true,
      "dynamicBindingPathList": [
        {
          "key": "borderRadius"
        },
        {
          "key": "boxShadow"
        }
      ],
      "dynamicHeight": "AUTO_HEIGHT",
      "dynamicTriggerPathList": [],
      "flexLayers": [],
      "isDisabled": false,
      "isLoading": false,
      "isVisible": true,
      "key": "vo8dpmm47p",
      "leftColumn": 0,
      "maxDynamicHeight": 9000,
      "minDynamicHeight": 4,
      "minHeight": 150,
      "minWidth": 450,
      "mobileBottomRow": 150,
      "mobileLeftColumn": 0,
      "mobileRightColumn": 243,
      "mobileTopRow": 0,
      "needsErrorInfo": false,
      "parentColumnSpace": 1,
      "parentId": "0qlukdr7oa",
      "parentRowSpace": 1,
      "renderMode": "CANVAS",
      "responsiveBehavior": "fill",
      "rightColumn": 243,
      "shouldScrollContents": false,
      "tabId": "tab1",
      "tabName": "Data",
      "topRow": 0,
      "type": "CANVAS_WIDGET",
      "version": 1,
      "widgetId": "4qj6ory8eq",
      "widgetName": "Canvas1"
    },
    {
      "borderRadius": "{{appsmith.theme.borderRadius.appBorderRadius}}",
      "bottomRow": 680,
      "boxShadow": "{{appsmith.theme.boxShadow.appBoxShadow}}",
      "canExtend": true,
      "detachFromLayout": true,
      "dynamicBindingPathList": [
        {
          "key": "borderRadius"
        },
        {
          "key": "boxShadow"
        }
      ],
      "dynamicHeight": "AUTO_HEIGHT",
      "dynamicTriggerPathList": [],
      "flexLayers": [],
      "isDisabled": false,
      "isLoading": false,
      "isVisible": true,
      "key": "vo8dpmm47p",
      "leftColumn": 0,
      "maxDynamicHeight": 9000,
      "minDynamicHeight": 4,
      "minHeight": 150,
      "minWidth": 450,
      "mobileBottomRow": 150,
      "mobileLeftColumn": 0,
      "mobileRightColumn": 243,
      "mobileTopRow": 0,
      "needsErrorInfo": false,
      "parentColumnSpace": 1,
      "parentId": "0qlukdr7oa",
      "parentRowSpace": 1,
      "renderMode": "CANVAS",
      "responsiveBehavior": "fill",
      "rightColumn": 243,
      "shouldScrollContents": false,
      "tabId": "tab2",
      "tabName": "Map",
      "topRow": 0,
      "type": "CANVAS_WIDGET",
      "version": 1,
      "widgetId": "11dxk86986",
      "widgetName": "Canvas2"
    },
    {
      "borderRadius": "{{appsmith.theme.borderRadius.appBorderRadius}}",
      "bottomRow": 680,
      "boxShadow": "{{appsmith.theme.boxShadow.appBoxShadow}}",
      "canExtend": false,
      "containerStyle": "none",
      "detachFromLayout": true,
      "dynamicBindingPathList": [
        {
          "key": "borderRadius"
        },
        {
          "key": "boxShadow"
        }
      ],
      "dynamicHeight": "AUTO_HEIGHT",
      "dynamicTriggerPathList": [],
      "flexLayers": [],
      "isLoading": false,
      "isVisible": true,
      "key": "vo8dpmm47p",
      "leftColumn": 0,
      "maxDynamicHeight": 9000,
      "minDynamicHeight": 4,
      "minHeight": 320,
      "minWidth": 450,
      "mobileBottomRow": 321,
      "mobileLeftColumn": 0,
      "mobileRightColumn": 850.5,
      "mobileTopRow": 1,
      "needsErrorInfo": false,
      "parentColumnSpace": 1,
      "parentId": "0qlukdr7oa",
      "parentRowSpace": 1,
      "renderMode": "CANVAS",
      "responsiveBehavior": "fill",
      "rightColumn": 850.5,
      "tabId": "tabz6wejh3fns",
      "tabName": "Map embeded",
      "topRow": 1,
      "type": "CANVAS_WIDGET",
      "version": 1,
      "widgetId": "t7unv8v00m",
      "widgetName": "Canvas3"
    },
    {
      "borderRadius": "{{appsmith.theme.borderRadius.appBorderRadius}}",
      "bottomRow": 680,
      "boxShadow": "{{appsmith.theme.boxShadow.appBoxShadow}}",
      "canExtend": false,
      "containerStyle": "none",
      "detachFromLayout": true,
      "dynamicBindingPathList": [
        {
          "key": "borderRadius"
        },
        {
          "key": "boxShadow"
        }
      ],
      "dynamicHeight": "AUTO_HEIGHT",
      "dynamicTriggerPathList": [],
      "flexLayers": [],
      "isLoading": false,
      "isVisible": true,
      "key": "cuznoj6rk2",
      "leftColumn": 0,
      "maxDynamicHeight": 9000,
      "minDynamicHeight": 4,
      "minHeight": 630,
      "minWidth": 450,
      "mobileBottomRow": 631,
      "mobileLeftColumn": 0,
      "mobileRightColumn": 850.5,
      "mobileTopRow": 1,
      "needsErrorInfo": false,
      "parentColumnSpace": 1,
      "parentId": "0qlukdr7oa",
      "parentRowSpace": 1,
      "renderMode": "CANVAS",
      "responsiveBehavior": "fill",
      "rightColumn": 850.5,
      "tabId": "tabzvp71gqu62",
      "tabName": "OpenLayer",
      "topRow": 1,
      "type": "CANVAS_WIDGET",
      "version": 1,
      "widgetId": "x1c72e5cse",
      "widgetName": "Canvas4"
    }
  ],
  "defaultTab": "Data",
  "dynamicBindingPathList": [
    {
      "key": "accentColor"
    }
  ],
  "dynamicHeight": "AUTO_HEIGHT",
  "dynamicTriggerPathList": [],
  "flexVerticalAlignment": "stretch",
  "isCanvas": true,
  "isLoading": false,
  "isVisible": true,
  "key": "79vfmq65pe",
  "leftColumn": 0,
  "maxDynamicHeight": 9000,
  "minDynamicHeight": 15,
  "minWidth": 450,
  "mobileBottomRow": 20,
  "mobileLeftColumn": 0,
  "mobileRightColumn": 18,
  "mobileTopRow": 5,
  "needsErrorInfo": false,
  "originalBottomRow": 72,
  "originalTopRow": 0,
  "parentColumnSpace": 13.5,
  "parentId": "0",
  "parentRowSpace": 10,
  "renderMode": "CANVAS",
  "responsiveBehavior": "fill",
  "rightColumn": 64,
  "shouldScrollContents": true,
  "shouldShowTabs": true,
  "tabsObj": {
    "tab1": {
      "id": "tab1",
      "index": 0,
      "isVisible": true,
      "label": "Data",
      "positioning": "vertical",
      "widgetId": "4qj6ory8eq"
    },
    "tab2": {
      "id": "tab2",
      "index": 1,
      "isVisible": true,
      "label": "Map",
      "positioning": "vertical",
      "widgetId": "11dxk86986"
    },
    "tabz6wejh3fns": {
      "id": "tabz6wejh3fns",
      "index": 2,
      "isVisible": true,
      "label": "Map embeded",
      "widgetId": "t7unv8v00m"
    },
    "tabzvp71gqu62": {
      "id": "tabzvp71gqu62",
      "index": 3,
      "isVisible": true,
      "label": "OpenLayer",
      "widgetId": "x1c72e5cse"
    }
  },
  "topRow": 0,
  "type": "TABS_WIDGET",
  "version": 3,
  "widgetId": "0qlukdr7oa",
  "widgetName": "Tabs1"
}