{
  "animateLoading": true,
  "borderRadius": "{{appsmith.theme.borderRadius.appBorderRadius}}",
  "bottomRow": 4,
  "disableLink": false,
  "dynamicBindingPathList": [
    {
      "key": "truncateButtonColor"
    },
    {
      "key": "borderRadius"
    }
  ],
  "dynamicHeight": "AUTO_HEIGHT",
  "dynamicTriggerPathList": [],
  "fontFamily": "Montserrat",
  "fontSize": "0.875rem",
  "fontStyle": "",
  "isLoading": false,
  "isVisible": true,
  "key": "bwcpvrq2li",
  "leftColumn": 27,
  "maxDynamicHeight": 9000,
  "minDynamicHeight": 4,
  "minWidth": 450,
  "mobileBottomRow": 4,
  "mobileLeftColumn": 39,
  "mobileRightColumn": 55,
  "mobileTopRow": 0,
  "needsErrorInfo": false,
  "originalBottomRow": 5,
  "originalTopRow": 0,
  "overflow": "NONE",
  "parentColumnSpace": 12.9765625,
  "parentId": "t7unv8v00m",
  "parentRowSpace": 10,
  "renderMode": "CANVAS",
  "responsiveBehavior": "fill",
  "rightColumn": 63,
  "shouldTruncate": false,
  "text": "https://developers.google.com/maps/documentation/embed/embedding-map?hl=fr#place_mode",
  "textAlign": "LEFT",
  "textColor": "#231F20",
  "topRow": 0,
  "truncateButtonColor": "{{appsmith.theme.colors.primaryColor}}",
  "type": "TEXT_WIDGET",
  "version": 1,
  "widgetId": "6fcyretsri",
  "widgetName": "Text1"
}