{
  "gitSyncId": "66cfa4c28eb6fc0fd11d8a6b_a1f4a3e3-9a10-4733-a897-bcae30b1dc10",
  "id": "Accueil_World_Bank",
  "pluginId": "restapi-plugin",
  "pluginType": "API",
  "unpublishedAction": {
    "actionConfiguration": {
      "autoGeneratedHeaders": [],
      "body": "",
      "bodyFormData": [],
      "encodeParamsToggle": true,
      "formData": {
        "apiContentType": "none"
      },
      "headers": [],
      "httpMethod": "GET",
      "httpVersion": "HTTP11",
      "paginationType": "NONE",
      "path": "/v2/country/all/indicator/SP.POP.TOTL",
      "pluginSpecifiedTemplates": [
        {
          "value": true
        }
      ],
      "queryParameters": [
        {
          "key": "format",
          "value": "json"
        },
        {
          "key": "per_page",
          "value": "200"
        },
        {
          "key": "date",
          "value": "2023"
        }
      ],
      "timeoutInMillisecond": 10000
    },
    "confirmBeforeExecute": false,
    "datasource": {
      "datasourceConfiguration": {
        "url": "https://api.worldbank.org"
      },
      "isAutoGenerated": false,
      "name": "DEFAULT_REST_DATASOURCE",
      "pluginId": "restapi-plugin"
    },
    "dynamicBindingPathList": [],
    "executeOnLoad": true,
    "name": "World_Bank",
    "pageId": "Accueil",
    "userSetOnLoad": false
  }
}